lucasex1/__init__.py
lucasex1/armazenamento.py
lucasex1/consulta.py
lucasex1/interação.py
lucasex1-0.0.1.dist-info/LICENSE.txt
lucasex1-0.0.1.dist-info/METADATA
lucasex1-0.0.1.dist-info/WHEEL
lucasex1-0.0.1.dist-info/top_level.txt
lucasex1-0.0.1.dist-info/RECORD
