Metadata-Version: 2.1
Name: lucasex1
Version: 0.0.1
Summary: Pacote python para exibir número de 1 a 9
Home-page: https://github.com
Author: Lucas Tavares de Jesus Borges
Author-email: lucas21070029@aluno.cesupa.br
License: MIT License
Keywords: Pacote
License-File: LICENSE.txt
